Workbook

Sheet Dashboard
A1: SkyGuard 财务仪表盘
A3: 年份 | B3: 收入 | C3: 毛利 | D3: EBITDA | E3: 经营现金流 | F3: 期末现金 | G3: 毛利率 | H3: 收入同比 | I3: 现金状态
A4: 2026 | B4: ='收入'!B28 | C4: ='成本费用'!B7 | D4: ='成本费用'!B14 | E4: ='现金流'!B10 | F4: ='现金流'!B11 | G4: ='成本费用'!B8 | H4: ='收入'!B29 | I4: ='现金流'!B12
A5: 2027 | B5: ='收入'!C28 | C5: ='成本费用'!C7 | D5: ='成本费用'!C14 | E5: ='现金流'!C10 | F5: ='现金流'!C11 | G5: ='成本费用'!C8 | H5: ='收入'!C29 | I5: ='现金流'!C12
A6: 2028 | B6: ='收入'!D28 | C6: ='成本费用'!D7 | D6: ='成本费用'!D14 | E6: ='现金流'!D10 | F6: ='现金流'!D11 | G6: ='成本费用'!D8 | H6: ='收入'!D29 | I6: ='现金流'!D12
A7: 2029 | B7: ='收入'!E28 | C7: ='成本费用'!E7 | D7: ='成本费用'!E14 | E7: ='现金流'!E10 | F7: ='现金流'!E11 | G7: ='成本费用'!E8 | H7: ='收入'!E29 | I7: ='现金流'!E12
A8: 2030 | B8: ='收入'!F28 | C8: ='成本费用'!F7 | D8: ='成本费用'!F14 | E8: ='现金流'!F10 | F8: ='现金流'!F11 | G8: ='成本费用'!F8 | H8: ='收入'!F29 | I8: ='现金流'!F12
A11: 模型状态 | B11: =Checks!B10 | D11: NPV | E11: ='投资评价'!B11 | G11: IRR | H11: ='投资评价'!B12

Sheet 假设
A1: SkyGuard 财务模型假设与口径
A3: 类别 | B3: 项目 | C3: 数值/口径 | D3: 说明 | E3: 来源
A4: 模型约定 | B4: 金额单位 | C4: 万元 | D4: 除特别注明外，收入、成本、现金流均以人民币万元表达。 | E4: 课程计划书财务分析要求
A5: 模型约定 | B5: 预测期 | C5: 2026-2030 | D5: 五年滚动预测，适合作为创业计划书的经营测算。 | E5: 课程计划书财务分析要求
A6: 模型约定 | B6: 估值日 | C6: 2026-07-05 | D6: 按当前课程提交节点生成模型。 | E6: 项目交付节点
A7: 关键输入 | B7: 折现率 | C7: 0.14 | D7: 用于 NPV 和敏感性测算。 | E7: 经营假设
A8: 关键输入 | B8: 所得税率 | C8: 0.15 | D8: 盈利年度简化税率，亏损年度不计所得税。 | E8: 经营假设
A9: 关键输入 | B9: 营运资本占收入增量比例 | C9: 0.08 | D9: 用于估算回款周期和应收占用。 | E9: 经营假设
A10: 关键输入 | B10: 资本开支率 | C10: 0.04 | D10: 轻资产平台必要设备、云资源和试点工具投入。 | E10: 经营假设
A11: 关键输入 | B11: 折旧摊销率 | C11: 0.03 | D11: 对资本化投入进行简化摊销。 | E11: 经营假设
A12: 关键输入 | B12: 客户成功费用率 | C12: 0.05 | D12: 随客户规模增加的规则维护、培训和复盘会议成本。 | E12: 经营假设
A13: 关键输入 | B13: 期初现金 | C13: 220 | D13: 项目启动资金和已有资源折算。 | E13: 经营假设
A14: 关键输入 | B14: 首轮融资流入 | C14: 450 | D14: 用于产品打磨、试点交付、数据治理和客户成功。 | E14: 融资假设
A15: 经营假设 | B15: Lite SaaS年费 | C15: 8-15万元/年，模型取12万元/年 | D15: 来自原始商业模型口径。 | E15: 经营假设
A16: 经营假设 | B16: Pro部署 | C16: 30-80万元/项目，模型按项目复杂度阶梯增长 | D16: 来自原始商业模型口径。 | E16: 经营假设
A17: 经营假设 | B17: Gov试点 | C17: 100-300万元/项目，谨慎计入首年无收入 | D17: 来自原始商业模型口径。 | E17: 经营假设
A18: 经营假设 | B18: 活动保障 | C18: 5-30万元/次，适合赛事、演唱会、会展 | D18: 来自原始商业模型口径。 | E18: 经营假设
A19: 经营假设 | B19: 航线评估 | C19: 3000-20000元/条，按批量航线折扣 | D19: 来自原始商业模型口径。 | E19: 经营假设
A20: 经营假设 | B20: 运维服务 | C20: 合同额10%-20%/年 | D20: 来自原始商业模型口径。 | E20: 经营假设
A21: 经营假设 | B21: 毛利率 | C21: 随SaaS、报告、运维占比提高逐年改善 | D21: 来自原始商业模型口径。 | E21: 经营假设

Sheet 收入
A1: 收入驱动模型
A3: 指标 | B3: 2026 | C3: 2027 | D3: 2028 | E3: 2029 | F3: 2030 | G3: 备注
A4: Lite SaaS客户数 | B4: 4 | C4: 14 | D4: 35 | E4: 65 | F4: 100 | G4: Lite SaaS年度客户数，蓝色单元格可调整。
A5: Lite SaaS年费 | B5: 12 | C5: 12 | D5: 12 | E5: 12 | F5: 12 | G5: 万元/年/客户
A6: Lite SaaS收入 | B6: =B4*B5 | C6: =C4*C5 | D6: =D4*D5 | E6: =E4*E5 | F6: =F4*F5 | G6: 由数量和单价公式计算。
A7: Pro部署项目数 | B7: 2 | C7: 7 | D7: 16 | E7: 25 | F7: 35 | G7: Pro部署年度项目数，蓝色单元格可调整。
A8: Pro部署客单价 | B8: 60 | C8: 60 | D8: 60 | E8: 60 | F8: 60 | G8: 万元/项目
A9: Pro部署收入 | B9: =B7*B8 | C9: =C7*C8 | D9: =D7*D8 | E9: =E7*E8 | F9: =F7*F8 | G9: 由数量和单价公式计算。
A10: Gov试点项目数 | B10: 0 | C10: 1 | D10: 3 | E10: 5 | F10: 7 | G10: Gov试点年度项目数，蓝色单元格可调整。
A11: Gov试点客单价 | B11: 200 | C11: 200 | D11: 200 | E11: 200 | F11: 214.3 | G11: 万元/项目
A12: Gov试点收入 | B12: =B10*B11 | C12: =C10*C11 | D12: =D10*D11 | E12: =E10*E11 | F12: =F10*F11 | G12: 由数量和单价公式计算。
A13: 活动保障场次 | B13: 4 | C13: 15 | D13: 35 | E13: 60 | F13: 87 | G13: 活动保障年度场次，蓝色单元格可调整。
A14: 活动保障客单价 | B14: 5 | C14: 6 | D14: 6 | E14: 6 | F14: 6 | G14: 万元/次
A15: 活动保障收入 | B15: =B13*B14 | C15: =C13*C14 | D15: =D13*D14 | E15: =E13*E14 | F15: =F13*F14 | G15: 由数量和单价公式计算。
A16: 航线评估条数 | B16: 40 | C16: 220 | D16: 600 | E16: 1200 | F16: 2133 | G16: 航线评估年度条数，蓝色单元格可调整。
A17: 航线评估单价 | B17: 0.3 | C17: 0.3 | D17: 0.3 | E17: 0.3 | F17: 0.3 | G17: 万元/条
A18: 航线评估收入 | B18: =B16*B17 | C18: =C16*C17 | D18: =D16*D17 | E18: =E16*E17 | F18: =F16*F17 | G18: 由数量和单价公式计算。
A19: 数据报告份数 | B19: 0 | C19: 12 | D19: 36 | E19: 80 | F19: 140 | G19: 数据报告年度份数，蓝色单元格可调整。
A20: 数据报告单价 | B20: 3 | C20: 3 | D20: 3 | E20: 3 | F20: 3 | G20: 万元/份
A21: 数据报告收入 | B21: =B19*B20 | C21: =C19*C20 | D21: =D19*D20 | E21: =E19*E20 | F21: =F19*F20 | G21: 由数量和单价公式计算。
A22: 运维服务客户数 | B22: 0 | C22: 7 | D22: 23 | E22: 51 | F22: 90 | G22: 运维服务年度客户数，蓝色单元格可调整。
A23: 运维服务年费 | B23: 6 | C23: 6 | D23: 6 | E23: 6 | F23: 6 | G23: 万元/年/客户
A24: 运维服务收入 | B24: =B22*B23 | C24: =C22*C23 | D24: =D22*D23 | E24: =E22*E23 | F24: =F22*F23 | G24: 由数量和单价公式计算。
A25: 设备接入接入点 | B25: 5 | C25: 20 | D25: 43 | E25: 70 | F25: 103 | G25: 设备接入年度接入点，蓝色单元格可调整。
A26: 设备接入单价 | B26: 6 | C26: 6 | D26: 6.05 | E26: 6 | F26: 6.02 | G26: 万元/点
A27: 设备接入收入 | B27: =B25*B26 | C27: =C25*C26 | D27: =D25*D26 | E27: =E25*E26 | F27: =F25*F26 | G27: 由数量和单价公式计算。
A28: 收入合计 | B28: =SUM(B6,B9,B12,B15,B18,B21,B24,B27) | C28: =SUM(C6,C9,C12,C15,C18,C21,C24,C27) | D28: =SUM(D6,D9,D12,D15,D18,D21,D24,D27) | E28: =SUM(E6,E9,E12,E15,E18,E21,E24,E27) | F28: =SUM(F6,F9,F12,F15,F18,F21,F24,F27) | G28: 公式汇总所有收入项。
A29: 收入同比 | B29: - | C29: =C28/B28-1 | D29: =D28/C28-1 | E29: =E28/D28-1 | F29: =F28/E28-1 | G29: 用于检查增长节奏是否过度激进。

Sheet 成本费用
A1: 成本费用与盈利模型
A3: 指标 | B3: 2026 | C3: 2027 | D3: 2028 | E3: 2029 | F3: 2030 | G3: 备注
A4: 收入合计 | B4: ='收入'!B28 | C4: ='收入'!C28 | D4: ='收入'!D28 | E4: ='收入'!E28 | F4: ='收入'!F28 | G4: 链接收入模型。
A5: 营业成本率 | B5: 0.52 | C5: 0.47 | D5: 0.42 | E5: 0.38 | F5: 0.35 | G5: 随订阅、报告和运维占比提升逐年改善。
A6: 营业成本 | B6: =B4*B5 | C6: =C4*C5 | D6: =D4*D5 | E6: =E4*E5 | F6: =F4*F5 | G6: 由收入和成本率计算。
A7: 毛利 | B7: =B4-B6 | C7: =C4-C6 | D7: =D4-D6 | E7: =E4-E6 | F7: =F4-F6 | G7: 收入减营业成本。
A8: 毛利率 | B8: =B7/B4 | C8: =C7/C4 | D8: =D7/D4 | E8: =E7/E4 | F8: =F7/F4 | G8: 用于检查 SaaS 化带来的毛利改善。
A9: 研发 | B9: 260 | C9: 360 | D9: 430 | E9: 520 | F9: 620 | G9: 产品、数据模型、部署工具和安全审计投入。
A10: 销售 | B10: 90 | C10: 180 | D10: 320 | E10: 480 | F10: 650 | G10: 试点拓展、渠道伙伴和客户沟通成本。
A11: 行政 | B11: 70 | C11: 90 | D11: 130 | E11: 170 | F11: 220 | G11: 公司管理、法务、财务和办公成本。
A12: 客户成功与运维 | B12: =B4*'假设'!$C$12 | C12: =C4*'假设'!$C$12 | D12: =D4*'假设'!$C$12 | E12: =E4*'假设'!$C$12 | F12: =F4*'假设'!$C$12 | G12: 按收入比例估算持续服务成本。
A13: 费用合计 | B13: =SUM(B9:B12) | C13: =SUM(C9:C12) | D13: =SUM(D9:D12) | E13: =SUM(E9:E12) | F13: =SUM(F9:F12) | G13: 研发、销售、行政、客户成功与运维合计。
A14: EBITDA | B14: =B7-B13 | C14: =C7-C13 | D14: =D7-D13 | E14: =E7-E13 | F14: =F7-F13 | G14: 毛利扣除经营费用。
A15: EBITDA率 | B15: =B14/B4 | C15: =C14/C4 | D15: =D14/D4 | E15: =E14/E4 | F15: =F14/F4 | G15: EBITDA / 收入。
A16: 所得税 | B16: =MAX(B14,0)*'假设'!$C$8 | C16: =MAX(C14,0)*'假设'!$C$8 | D16: =MAX(D14,0)*'假设'!$C$8 | E16: =MAX(E14,0)*'假设'!$C$8 | F16: =MAX(F14,0)*'假设'!$C$8 | G16: 盈利年度按假设税率估算。
A17: 净利润 | B17: =B14-B16 | C17: =C14-C16 | D17: =D14-D16 | E17: =E14-E16 | F17: =F14-F16 | G17: 税后经营结果。

Sheet 现金流
A1: 现金流与资金 runway
A3: 指标 | B3: 2026 | C3: 2027 | D3: 2028 | E3: 2029 | F3: 2030 | G3: 备注
A4: 期初现金 | B4: ='假设'!$C$13 | C4: =B11 | D4: =C11 | E4: =D11 | F4: =E11 | G4: 首年来自假设，后续链接上一年期末现金。
A5: 融资流入 | B5: ='假设'!$C$14 | C5: 0 | D5: 0 | E5: 0 | F5: 0 | G5: 默认首年融资，后续可按实际调整。
A6: 净利润 | B6: ='成本费用'!B17 | C6: ='成本费用'!C17 | D6: ='成本费用'!D17 | E6: ='成本费用'!E17 | F6: ='成本费用'!F17
A7: 折旧摊销 | B7: ='收入'!B28*'假设'!$C$11 | C7: ='收入'!C28*'假设'!$C$11 | D7: ='收入'!D28*'假设'!$C$11 | E7: ='收入'!E28*'假设'!$C$11 | F7: ='收入'!F28*'假设'!$C$11
A8: 营运资本占用 | B8: =-'收入'!B28*'假设'!$C$9 | C8: =-('收入'!C28-'收入'!B28)*'假设'!$C$9 | D8: =-('收入'!D28-'收入'!C28)*'假设'!$C$9 | E8: =-('收入'!E28-'收入'!D28)*'假设'!$C$9 | F8: =-('收入'!F28-'收入'!E28)*'假设'!$C$9
A9: 资本开支 | B9: =-'收入'!B28*'假设'!$C$10 | C9: =-'收入'!C28*'假设'!$C$10 | D9: =-'收入'!D28*'假设'!$C$10 | E9: =-'收入'!E28*'假设'!$C$10 | F9: =-'收入'!F28*'假设'!$C$10
A10: 经营现金流 | B10: =SUM(B6:B9) | C10: =SUM(C6:C9) | D10: =SUM(D6:D9) | E10: =SUM(E6:E9) | F10: =SUM(F6:F9) | G10: 净利润 + 折旧摊销 - 营运资本占用 - 资本开支。
A11: 期末现金 | B11: =B4+B5+B10 | C11: =C4+C5+C10 | D11: =D4+D5+D10 | E11: =E4+E5+E10 | F11: =F4+F5+F10
A12: 现金警戒 | B12: =IF(B11<0,"需融资","OK") | C12: =IF(C11<0,"需融资","OK") | D12: =IF(D11<0,"需融资","OK") | E12: =IF(E11<0,"需融资","OK") | F12: =IF(F11<0,"需融资","OK") | G12: 现金为负时提示需融资。

Sheet 情景
A1: 情景收入与现金压力测试
A3: 情景 | B3: 收入乘数 | C3: 2026 | D3: 2027 | E3: 2028 | F3: 2029 | G3: 2030 | H3: 2030期末现金
A4: 保守 | B4: 0.72 | C4: ='收入'!B28*$B4 | D4: ='收入'!C28*$B4 | E4: ='收入'!D28*$B4 | F4: ='收入'!E28*$B4 | G4: ='收入'!F28*$B4 | H4: ='现金流'!F11*$B4
A5: 基准 | B5: 1 | C5: ='收入'!B28*$B5 | D5: ='收入'!C28*$B5 | E5: ='收入'!D28*$B5 | F5: ='收入'!E28*$B5 | G5: ='收入'!F28*$B5 | H5: ='现金流'!F11*$B5
A6: 乐观 | B6: 1.34 | C6: ='收入'!B28*$B6 | D6: ='收入'!C28*$B6 | E6: ='收入'!D28*$B6 | F6: ='收入'!E28*$B6 | G6: ='收入'!F28*$B6 | H6: ='现金流'!F11*$B6

Sheet 投资评价
A1: 投资评价：NPV / IRR / 回收期
A3: 折现率 | B3: ='假设'!$C$7
A4: 评价口径 | B4: 首轮融资作为期初投入，经营现金流作为项目回收口径。
A7: 年份 | B7: 2025初始 | C7: 2026 | D7: 2027 | E7: 2028 | F7: 2029 | G7: 2030
A8: 项目现金流 | B8: =-'假设'!$C$14 | C8: ='现金流'!B10 | D8: ='现金流'!C10 | E8: ='现金流'!D10 | F8: ='现金流'!E10 | G8: ='现金流'!F10
A9: 累计现金流 | B9: =B8 | C9: =B9+C8 | D9: =C9+D8 | E9: =D9+E8 | F9: =E9+F8 | G9: =F9+G8
A11: NPV | B11: =NPV($B$3,C8:G8)+B8
A12: IRR | B12: =IFERROR(IRR(B8:G8),"需继续验证")
A13: 静态回收期 | B13: =IF(B9>=0,B7,IF(C9>=0,B7+ABS(B9)/C8,IF(D9>=0,C7+ABS(C9)/D8,IF(E9>=0,D7+ABS(D9)/E8,IF(F9>=0,E7+ABS(E9)/F8,IF(G9>=0,F7+ABS(F9)/G8,"2030后"))))))
A14: 2030期末现金 | B14: ='现金流'!F11

Sheet 敏感性
A1: 敏感性：收入乘数 x 折现率
A3: 收入乘数 / 折现率 | B3: 0.1 | C3: 0.12 | D3: 0.14 | E3: 0.16 | F3: 0.18 | G3: 说明
A4: 0.8 | B4: =NPV(B$3,'现金流'!$B$10*$A4,'现金流'!$C$10*$A4,'现金流'!$D$10*$A4,'现金流'!$E$10*$A4,'现金流'!$F$10*$A4)+'投资评价'!$B$8 | C4: =NPV(C$3,'现金流'!$B$10*$A4,'现金流'!$C$10*$A4,'现金流'!$D$10*$A4,'现金流'!$E$10*$A4,'现金流'!$F$10*$A4)+'投资评价'!$B$8 | D4: =NPV(D$3,'现金流'!$B$10*$A4,'现金流'!$C$10*$A4,'现金流'!$D$10*$A4,'现金流'!$E$10*$A4,'现金流'!$F$10*$A4)+'投资评价'!$B$8 | E4: =NPV(E$3,'现金流'!$B$10*$A4,'现金流'!$C$10*$A4,'现金流'!$D$10*$A4,'现金流'!$E$10*$A4,'现金流'!$F$10*$A4)+'投资评价'!$B$8 | F4: =NPV(F$3,'现金流'!$B$10*$A4,'现金流'!$C$10*$A4,'现金流'!$D$10*$A4,'现金流'!$E$10*$A4,'现金流'!$F$10*$A4)+'投资评价'!$B$8 | G4: 收入乘数调整经营现金流，折现率调整项目现值。
A5: 0.9 | B5: =NPV(B$3,'现金流'!$B$10*$A5,'现金流'!$C$10*$A5,'现金流'!$D$10*$A5,'现金流'!$E$10*$A5,'现金流'!$F$10*$A5)+'投资评价'!$B$8 | C5: =NPV(C$3,'现金流'!$B$10*$A5,'现金流'!$C$10*$A5,'现金流'!$D$10*$A5,'现金流'!$E$10*$A5,'现金流'!$F$10*$A5)+'投资评价'!$B$8 | D5: =NPV(D$3,'现金流'!$B$10*$A5,'现金流'!$C$10*$A5,'现金流'!$D$10*$A5,'现金流'!$E$10*$A5,'现金流'!$F$10*$A5)+'投资评价'!$B$8 | E5: =NPV(E$3,'现金流'!$B$10*$A5,'现金流'!$C$10*$A5,'现金流'!$D$10*$A5,'现金流'!$E$10*$A5,'现金流'!$F$10*$A5)+'投资评价'!$B$8 | F5: =NPV(F$3,'现金流'!$B$10*$A5,'现金流'!$C$10*$A5,'现金流'!$D$10*$A5,'现金流'!$E$10*$A5,'现金流'!$F$10*$A5)+'投资评价'!$B$8 | G5: 收入乘数调整经营现金流，折现率调整项目现值。
A6: 1 | B6: =NPV(B$3,'现金流'!$B$10*$A6,'现金流'!$C$10*$A6,'现金流'!$D$10*$A6,'现金流'!$E$10*$A6,'现金流'!$F$10*$A6)+'投资评价'!$B$8 | C6: =NPV(C$3,'现金流'!$B$10*$A6,'现金流'!$C$10*$A6,'现金流'!$D$10*$A6,'现金流'!$E$10*$A6,'现金流'!$F$10*$A6)+'投资评价'!$B$8 | D6: =NPV(D$3,'现金流'!$B$10*$A6,'现金流'!$C$10*$A6,'现金流'!$D$10*$A6,'现金流'!$E$10*$A6,'现金流'!$F$10*$A6)+'投资评价'!$B$8 | E6: =NPV(E$3,'现金流'!$B$10*$A6,'现金流'!$C$10*$A6,'现金流'!$D$10*$A6,'现金流'!$E$10*$A6,'现金流'!$F$10*$A6)+'投资评价'!$B$8 | F6: =NPV(F$3,'现金流'!$B$10*$A6,'现金流'!$C$10*$A6,'现金流'!$D$10*$A6,'现金流'!$E$10*$A6,'现金流'!$F$10*$A6)+'投资评价'!$B$8 | G6: 收入乘数调整经营现金流，折现率调整项目现值。
A7: 1.1 | B7: =NPV(B$3,'现金流'!$B$10*$A7,'现金流'!$C$10*$A7,'现金流'!$D$10*$A7,'现金流'!$E$10*$A7,'现金流'!$F$10*$A7)+'投资评价'!$B$8 | C7: =NPV(C$3,'现金流'!$B$10*$A7,'现金流'!$C$10*$A7,'现金流'!$D$10*$A7,'现金流'!$E$10*$A7,'现金流'!$F$10*$A7)+'投资评价'!$B$8 | D7: =NPV(D$3,'现金流'!$B$10*$A7,'现金流'!$C$10*$A7,'现金流'!$D$10*$A7,'现金流'!$E$10*$A7,'现金流'!$F$10*$A7)+'投资评价'!$B$8 | E7: =NPV(E$3,'现金流'!$B$10*$A7,'现金流'!$C$10*$A7,'现金流'!$D$10*$A7,'现金流'!$E$10*$A7,'现金流'!$F$10*$A7)+'投资评价'!$B$8 | F7: =NPV(F$3,'现金流'!$B$10*$A7,'现金流'!$C$10*$A7,'现金流'!$D$10*$A7,'现金流'!$E$10*$A7,'现金流'!$F$10*$A7)+'投资评价'!$B$8 | G7: 收入乘数调整经营现金流，折现率调整项目现值。
A8: 1.2 | B8: =NPV(B$3,'现金流'!$B$10*$A8,'现金流'!$C$10*$A8,'现金流'!$D$10*$A8,'现金流'!$E$10*$A8,'现金流'!$F$10*$A8)+'投资评价'!$B$8 | C8: =NPV(C$3,'现金流'!$B$10*$A8,'现金流'!$C$10*$A8,'现金流'!$D$10*$A8,'现金流'!$E$10*$A8,'现金流'!$F$10*$A8)+'投资评价'!$B$8 | D8: =NPV(D$3,'现金流'!$B$10*$A8,'现金流'!$C$10*$A8,'现金流'!$D$10*$A8,'现金流'!$E$10*$A8,'现金流'!$F$10*$A8)+'投资评价'!$B$8 | E8: =NPV(E$3,'现金流'!$B$10*$A8,'现金流'!$C$10*$A8,'现金流'!$D$10*$A8,'现金流'!$E$10*$A8,'现金流'!$F$10*$A8)+'投资评价'!$B$8 | F8: =NPV(F$3,'现金流'!$B$10*$A8,'现金流'!$C$10*$A8,'现金流'!$D$10*$A8,'现金流'!$E$10*$A8,'现金流'!$F$10*$A8)+'投资评价'!$B$8 | G8: 收入乘数调整经营现金流，折现率调整项目现值。

Sheet Checks
A1: 模型校验
A3: 检查项 | B3: 实际值 | C3: 期望值 | D3: 差异 | E3: 状态 | F3: 修复提示
A4: 2028收入合计 | B4: ='收入'!D28 | C4: =SUM(D6,D9,D12,D15,D18,D21,D24,D27) | D4: =B4-C4 | E4: =IF(ABS(D4)<0.01,"OK","检查") | F4: 检查收入组件是否遗漏。
A5: 2028毛利 | B5: ='成本费用'!D7 | C5: ='成本费用'!D4-'成本费用'!D6 | D5: =B5-C5 | E5: =IF(ABS(D5)<0.01,"OK","检查") | F5: 检查成本费用表公式。
A6: 2028期末现金 | B6: ='现金流'!D11 | C6: ='现金流'!D4+'现金流'!D5+'现金流'!D10 | D6: =B6-C6 | E6: =IF(ABS(D6)<0.01,"OK","检查") | F6: 检查现金流勾稽。
A7: 2030基准情景收入 | B7: =情景!F5 | C7: ='收入'!F28 | D7: =B7-C7 | E7: =IF(ABS(D7)<0.01,"OK","检查") | F7: 检查情景表基准乘数。
A8: 资料来源数量 | B8: =COUNTA('资料来源'!A:A)-1 | C8: 32 | D8: =B8-C8 | E8: =IF(ABS(D8)<0.01,"OK","检查") | F8: 检查来源索引是否为空。
A10: 模型状态 | B10: =IF(COUNTIF(E4:E8,"检查")=0,"OK","存在需检查项")

Sheet 资料来源
A1: 资料名称 | B1: 发布主体 | C1: 时间 | D1: 链接 | E1: 用途 | F1: 资料类型
A2: 国务院关于《2024年政府工作报告》的公开文本 | B2: 中国政府网 | C2: 2024-03 | D2: https://www.gov.cn/yaowen/liebiao/202403/content_6939153.htm | E2: 确认低空经济被列为新增长引擎相关表述。 | F2: official_policy
A3: 无人驾驶航空器飞行管理暂行条例 | B3: 国务院、中央军委；中国民用航空局公开 | C3: 2023-06发布，2024-01施行 | D3: https://www.caac.gov.cn/XXGK/XXGK/FLFG/202401/t20240115_222642.html | E3: 支撑无人驾驶航空器飞行活动、身份、空域、记录和安全管理边界。 | F3: official_regulation
A4: 通用航空装备创新应用实施方案（2024-2030年） | B4: 工业和信息化部等部门 | C4: 2024 | D4: https://wap.miit.gov.cn/zwgk/zcwj/wjfb/tz/art/2024/art_4ce8d09c15ee4fb1aefc3d5dfbbb6584.html | E4: 支撑低空装备、应用示范、公共服务和运行保障场景。 | F4: official_policy
A5: 低空经济及其核心产业统计分类（试行） | B5: 国家发展改革委 | C5: 2025-12 | D5: https://www.ndrc.gov.cn/xxgk/zcfb/tz/202512/t20251226_1402669.html | E5: 用于界定低空经济产业边界和统计口径。 | F5: official_policy
A6: 低空经济政策法规全量数据.csv | B6: 本地整理数据集或公开数据源 | C6: 按文件记录年份 | D6: 数据以及图\_整理\数据\低空经济政策法规全量数据.csv | E6: 按年份、地区和政策类型聚合，用于政策窗口与区域机会分析。 | F6: local_dataset
A7: 低空经济招投标项目全量数据.csv | B7: 本地整理数据集或公开数据源 | C7: 按文件记录年份 | D7: 数据以及图\_整理\数据\低空经济招投标项目全量数据.csv | E7: 按预算、项目类型和省份聚合，用于市场温度和采购场景判断。 | F7: local_dataset
A8: 低空经济专利全量数据.csv | B8: 本地整理数据集或公开数据源 | C8: 按文件记录年份 | D8: 数据以及图\_整理\数据\低空经济专利全量数据.csv | E8: 按年份、IPC和申请人聚合，用于技术活跃度分析。 | F8: local_dataset
A9: 低空经济相关企业全量数据.csv | B9: 本地整理数据集或公开数据源 | C9: 按文件记录年份 | D9: 数据以及图\_整理\数据\低空经济相关企业全量数据.csv | E9: 按省份、行业和注册年份聚合，用于产业生态分析。 | F9: local_dataset
A10: 低空经济产业链上下游数据.csv | B10: 本地整理数据集或公开数据源 | C10: 按文件记录年份 | D10: 数据以及图\_整理\数据\低空经济产业链上下游数据.csv | E10: 按产业链环节和细分领域聚合，用于伙伴生态分析。 | F10: local_dataset
A11: 各省低空经济指数数据（1990-2024）.csv | B11: 本地整理数据集或公开数据源 | C11: 按文件记录年份 | D11: 数据以及图\_整理\数据\各省低空经济指数数据（1990-2024）.csv | E11: 用于省域指数、区域分层和市场进入顺序分析。 | F11: local_dataset
A12: 低空安全事件与监管案例数据.csv | B12: 本地整理数据集或公开数据源 | C12: 按文件记录年份 | D12: 数据以及图\_整理\数据\低空安全事件与监管案例数据.csv | E12: 用于安全事件类型、严重程度和监管处置分析。 | F12: local_dataset
... A24: 广东省推动低空经济高质量发展行动方案（2024—2026年） | B24: 地方政府/主管部门公开资料 | C24: 2026 | D24: https://www.thnet.gov.cn/zjth/tzth/tzzc/sszc/content/post_9836185.html | E24: 用于地方低空经济目标、平台建设、航线和起降网络规划分析。 | F24: local_policy_or_case
A25: 广州市低空经济发展实施方案 | B25: 地方政府/主管部门公开资料 | D25: https://www.gz.gov.cn/zwgk/fggw/sfbgtwj/content/post_9743866.html | E25: 用于地方低空经济目标、平台建设、航线和起降网络规划分析。 | F25: local_policy_or_case
A26: 低空经济监管沙盒X | B26: 地方政府/主管部门公开资料 | D26: https://www.tlb.gov.hk/tc/highlights/transport/low-altitude.html | E26: 用于地方低空经济目标、平台建设、航线和起降网络规划分析。 | F26: local_policy_or_case
A27: 南通市低空经济高质量发展行动方案 | B27: 地方政府/主管部门公开资料 | C27: 2027 | D27: https://www.nantong.gov.cn/ntsrmzf/szfbwj/content/f6d67b3b-25c0-4b89-83f1-3794a28f3812.html | E27: 用于地方低空经济目标、平台建设、航线和起降网络规划分析。 | F27: local_policy_or_case
A28: 上海市低空经济产业高质量发展行动方案（草案） | B28: 地方政府/主管部门公开资料 | C28: 2027 | D28: https://www.sheitc.sh.gov.cn/qtzx/20241009/9336828aaeb3481bbf4733c8e607a527.html | E28: 用于地方低空经济目标、平台建设、航线和起降网络规划分析。 | F28: local_policy_or_case
A29: 上海“五个一”低空飞行安全监管体系公开报道 | B29: 地方政府/主管部门公开资料 | C29: 2026 | D29: https://www.mot.gov.cn/xinwen/jiaotongyaowen/202601/t20260122_4198498.html | E29: 用于地方低空经济目标、平台建设、航线和起降网络规划分析。 | F29: local_policy_or_case
A30: 深圳市低空基础设施高质量建设方案（2024—2026年） | B30: 地方政府/主管部门公开资料 | C30: 2026 | D30: https://fgw.sz.gov.cn/gkmlpt/content/12/12305/post_12305044.html | E30: 用于地方低空经济目标、平台建设、航线和起降网络规划分析。 | F30: local_policy_or_case
A31: 深圳市低空基础设施高质量建设方案（2024—2026年） | B31: 地方政府/主管部门公开资料 | C31: 2026 | D31: https://fgw.sz.gov.cn/zwgk/qt/tzgg/content/post_12305044.html | E31: 用于地方低空经济目标、平台建设、航线和起降网络规划分析。 | F31: local_policy_or_case
A32: 苏州市低空经济高质量发展实施方案（2024～2026年） | B32: 地方政府/主管部门公开资料 | C32: 2026 | D32: https://www.suzhou.gov.cn/szsrmzf/zfbgswj/202402/1ea65ae34733413ba188c04f8690267a.shtml | E32: 用于地方低空经济目标、平台建设、航线和起降网络规划分析。 | F32: local_policy_or_case
A33: 苏州市低空经济高质量发展实施方案（2024—2026年） | B33: 地方政府/主管部门公开资料 | C33: 2026 | D33: https://www.suzhou.gov.cn/szsrmzf/zfbgswj/202402/1ea65ae34733413ba188c04f8690267a.shtml | E33: 用于地方低空经济目标、平台建设、航线和起降网络规划分析。 | F33: local_policy_or_case
